Workbook

Sheet All Sessions
A1: Event No. | B1: Session | C1: Event Title | D1: Event Series / Programme | E1: Delivery Mode | F1: Venue / Location (as listed) | G1: Date | H1: Day | I1: Start Time | J1: End Time | K1: Duration (hrs) | L1: Description | M1: Featured Organisation (logo shown) | N1: Listing Page (results) | O1: Source
A2: 1 | B2: 1 of 3 | C2: eCareersGrad MasterClass: UK Grad Job & Internship Success: The Essential Guide | D2: eCareersGrad MasterClass | E2: Virtual | F2: Virtual event / Online webinar | G2: 46303 | H2: =TEXT(G2,"ddd") -> Thu | I2: 0.50694444 | J2: 0.54166667 | K2: =ROUND((J2-I2)*24,2) -> 0.83 | L2: An information session delivered by eCareersGrad with time for questions and answers. | N2: 1-100 | O2: UCL Careers (uclcareers.targetconnect.net), captured 13-Oct-2026
A3: 1 | B3: 2 of 3 | C3: eCareersGrad MasterClass: UK Grad Job & Internship Success: The Essential Guide | D3: eCareersGrad MasterClass | E3: Virtual | F3: Virtual event / Online webinar | G3: 46309 | H3: =TEXT(G3,"ddd") -> Wed | I3: 0.50694444 | J3: 0.54166667 | K3: =ROUND((J3-I3)*24,2) -> 0.83 | L3: An information session delivered by eCareersGrad with time for questions and answers. | N3: 1-100 | O3: UCL Careers (uclcareers.targetconnect.net), captured 13-Oct-2026
A4: 1 | B4: 3 of 3 | C4: eCareersGrad MasterClass: UK Grad Job & Internship Success: The Essential Guide | D4: eCareersGrad MasterClass | E4: Virtual | F4: Virtual event / Online webinar | G4: 46323 | H4: =TEXT(G4,"ddd") -> Wed | I4: 0.50694444 | J4: 0.54166667 | K4: =ROUND((J4-I4)*24,2) -> 0.83 | L4: An information session delivered by eCareersGrad with time for questions and answers. | N4: 1-100 | O4: UCL Careers (uclcareers.targetconnect.net), captured 13-Oct-2026
A5: 2 | B5: 1 of 6 | C5: eCareersGrad MasterClass: International Students: Target the Right UK Employer SPONSOR | D5: eCareersGrad MasterClass | E5: Virtual | F5: Virtual event / Online webinar | G5: 46303 | H5: =TEXT(G5,"ddd") -> Thu | I5: 0.54861111 | J5: 0.58333333 | K5: =ROUND((J5-I5)*24,2) -> 0.83 | L5: An information session delivered by eCareersGrad with time for questions and answers. | N5: 1-100 | O5: UCL Careers (uclcareers.targetconnect.net), captured 13-Oct-2026
A6: 2 | B6: 2 of 6 | C6: eCareersGrad MasterClass: International Students: Target the Right UK Employer SPONSOR | D6: eCareersGrad MasterClass | E6: Virtual | F6: Virtual event / Online webinar | G6: 46309 | H6: =TEXT(G6,"ddd") -> Wed | I6: 0.54861111 | J6: 0.58333333 | K6: =ROUND((J6-I6)*24,2) -> 0.83 | L6: An information session delivered by eCareersGrad with time for questions and answers. | N6: 1-100 | O6: UCL Careers (uclcareers.targetconnect.net), captured 13-Oct-2026
A7: 2 | B7: 3 of 6 | C7: eCareersGrad MasterClass: International Students: Target the Right UK Employer SPONSOR | D7: eCareersGrad MasterClass | E7: Virtual | F7: Virtual event / Online webinar | G7: 46315 | H7: =TEXT(G7,"ddd") -> Tue | I7: 0.54861111 | J7: 0.58333333 | K7: =ROUND((J7-I7)*24,2) -> 0.83 | L7: An information session delivered by eCareersGrad with time for questions and answers. | N7: 1-100 | O7: UCL Careers (uclcareers.targetconnect.net), captured 13-Oct-2026
A8: 2 | B8: 4 of 6 | C8: eCareersGrad MasterClass: International Students: Target the Right UK Employer SPONSOR | D8: eCareersGrad MasterClass | E8: Virtual | F8: Virtual event / Online webinar | G8: 46323 | H8: =TEXT(G8,"ddd") -> Wed | I8: 0.54861111 | J8: 0.58333333 | K8: =ROUND((J8-I8)*24,2) -> 0.83 | L8: An information session delivered by eCareersGrad with time for questions and answers. | N8: 1-100 | O8: UCL Careers (uclcareers.targetconnect.net), captured 13-Oct-2026
A9: 2 | B9: 5 of 6 | C9: eCareersGrad MasterClass: International Students: Target the Right UK Employer SPONSOR | D9: eCareersGrad MasterClass | E9: Virtual | F9: Virtual event / Online webinar | G9: 46335 | H9: =TEXT(G9,"ddd") -> Mon | I9: 0.54861111 | J9: 0.58333333 | K9: =ROUND((J9-I9)*24,2) -> 0.83 | L9: An information session delivered by eCareersGrad with time for questions and answers. | N9: 1-100 | O9: UCL Careers (uclcareers.targetconnect.net), captured 13-Oct-2026
A10: 2 | B10: 6 of 6 | C10: eCareersGrad MasterClass: International Students: Target the Right UK Employer SPONSOR | D10: eCareersGrad MasterClass | E10: Virtual | F10: Virtual event / Online webinar | G10: 46352 | H10: =TEXT(G10,"ddd") -> Thu | I10: 0.54861111 | J10: 0.58333333 | K10: =ROUND((J10-I10)*24,2) -> 0.83 | L10: An information session delivered by eCareersGrad with time for questions and answers. | N10: 1-100 | O10: UCL Careers (uclcareers.targetconnect.net), captured 13-Oct-2026
A11: 3 | B11: 1 of 1 | C11: Career Lab - Networking Preparation and Practice | D11: Career Lab | E11: On Campus | F11: On Campus: Canary Wharf Level 49, 49.02E Seminar Room | G11: 46308 | H11: =TEXT(G11,"ddd") -> Tue | I11: 0.39583333 | J11: 0.45833333 | K11: =ROUND((J11-I11)*24,2) -> 1.5 | L11: Work on your elevator pitch and practice your networking skills to make a fantastic first impression with employers. | N11: 1-100 | O11: UCL Careers (uclcareers.targetconnect.net), captured 13-Oct-2026
A12: 4 | B12: 1 of 1 | C12: Discover CASETiFY: Global Management Trainee Program 2027 Information Session | D12: Other / Employer-led event | E12: Virtual | F12: Virtual event / Online webinar | G12: 46308 | H12: =TEXT(G12,"ddd") -> Tue | I12: 0.5 | J12: 0.5625 | K12: =ROUND((J12-I12)*24,2) -> 1.5 | L12: Join us to learn more about CASETiFY's rapid global growth, hear first-hand experiences from our current Management Trainees, and get exclusive tips on how to apply for the 2027 intake. | N12: 1-100 | O12: UCL Careers (uclcareers.targetconnect.net), captured 13-Oct-2026
A13: 5 | B13: 1 of 1 | C13: Skills East: Online Job search strategy and LinkedIn | D13: Skills East | E13: Virtual | F13: Virtual event / Online webinar | G13: 46308 | H13: =TEXT(G13,"ddd") -> Tue | I13: 0.5 | J13: 0.54166667 | K13: =ROUND((J13-I13)*24,2) -> 1 | L13: In this online session you will have the opportunity to learn about building a job search strategy. This session will help you in terms of applications for jobs or internships as well as using LinkedIn as part of this process. | N13: 1-100 | O13: UCL Careers (uclcareers.targetconnect.net), captured 13-Oct-2026
A14: 6 | B14: 1 of 1 | C14: Career Essentials Group Work: CV Session | D14: Career Essentials Group Work | E14: On Campus | F14: On Campus: UCL Careers - 4th Floor Seminar Room (413) | G14: 46308 | H14: =TEXT(G14,"ddd") -> Tue | I14: 0.54166667 | J14: 0.57638889 | K14: =ROUND((J14-I14)*24,2) -> 0.83 | L14: Small group work Career Essentials session focusing on learning the key concepts that make up a good CV and getting feedback on your own CV from UCL Careers staff and peers. | N14: 1-100 | O14: UCL Careers (uclcareers.targetconnect.net), captured 13-Oct-2026
A15: 7 | B15: 1 of 1 | C15: Career Essentials: Improve Your CV | D15: Career Essentials | E15: Not stated | G15: 46308 | H15: =TEXT(G15,"ddd") -> Tue | I15: 0.54166667 | J15: 0.58333333 | K15: =ROUND((J15-I15)*24,2) -> 1 | L15: Strengthen your CV by learning how to grab an employer's interest and showcase your most relevant experiences. | N15: 1-100 | O15: UCL Careers (uclcareers.targetconnect.net), captured 13-Oct-2026
A16: 8 | B16: 1 of 1 | C16: Life & Health Sciences: Job Hunting and LinkedIn | D16: Life & Health Sciences | E16: Virtual | F16: Virtual event / Online webinar | G16: 46308 | H16: =TEXT(G16,"ddd") -> Tue | I16: 0.70833333 | J16: 0.75 | K16: =ROUND((J16-I16)*24,2) -> 1 | L16: Make LinkedIn work for your career. This session for Life and Health Sciences students explores how to find jobs, research organisations and professionals, uncover hidden opportunities, and strengthen your personal brand. | N16: 1-100 | O16: UCL Careers (uclcareers.targetconnect.net), captured 13-Oct-2026
A17: 9 | B17: 1 of 1 | C17: Meet the Deloitte Team at UCL East | D17: Other / Employer-led event | E17: On Campus | F17: UCL East Campus: Marshgate Building: Room 118 | G17: 46308 | H17: =TEXT(G17,"ddd") -> Tue | I17: 0.75 | J17: 0.875 | K17: =ROUND((J17-I17)*24,2) -> 3 | L17: Explore career journeys, develop your interview skills and practise with Deloitte | N17: 1-100 | O17: UCL Careers (uclcareers.targetconnect.net), captured 13-Oct-2026
A18: 10 | B18: 1 of 1 | C18: Buy Side Panel - Investment, Risk and Infrastructure Credit | D18: Other / Employer-led event | E18: On Campus | F18: On Campus: Canary Wharf Level 49, 49.01 Teaching Room | G18: 46309 | H18: =TEXT(G18,"ddd") -> Wed | I18: 0.53125 | J18: 0.59375 | K18: =ROUND((J18-I18)*24,2) -> 1.5 | L18: Senior professionals from Edmond De Rothschild, Janus Henderson, and Millennium share insights from their careers, take questions from the audience. There will also be time for more informal networking. | N18: 1-100 | O18: UCL Careers (uclcareers.targetconnect.net), captured 13-Oct-2026
A19: 11 | B19: 1 of 1 | C19: Overview of Global Consulting with James Brown from Savitas | D19: Other / Employer-led event | E19: Virtual | F19: Virtual event / Online webinar | G19: 46309 | H19: =TEXT(G19,"ddd") -> Wed | I19: 0.53125 | J19: 0.59375 | K19: =ROUND((J19-I19)*24,2) -> 1.5 | L19: Explore the range of options in and ways to enter the consulting industry in a global context | N19: 1-100 | O19: UCL Careers (uclcareers.targetconnect.net), captured 13-Oct-2026
A20: 12 | B20: 1 of 1 | C20: Employer-Led Skills Panel : Succeeding at Interviews with graduate recruiters | D20: Employer-led Skills Programme | E20: On Campus | F20: On Campus: UCL Careers - 4th Floor Seminar Room (413) | G20: 46309 | H20: =TEXT(G20,"ddd") -> Wed | I20: 0.54166667 | J20: 0.60416667 | K20: =ROUND((J20-I20)*24,2) -> 1.5 | L20: Employer-led skills panel discussion on how to succeed at interview with graduate employers | N20: 1-100 | O20: UCL Careers (uclcareers.targetconnect.net), captured 13-Oct-2026
A21: 13 | B21: 1 of 1 | C21: Career Essentials Group Work: Using STAR to Showcase Skills | D21: Career Essentials Group Work | E21: Virtual | F21: Virtual event / Online webinar | G21: 46309 | H21: =TEXT(G21,"ddd") -> Wed | I21: 0.54166667 | J21: 0.57638889 | K21: =ROUND((J21-I21)*24,2) -> 0.83 | L21: Small group work Career Essentials session focusing on learning the STAR technique, which can be used as a tool during interviews to help answer questions and showcase your skills. | N21: 1-100 | O21: UCL Careers (uclcareers.targetconnect.net), captured 13-Oct-2026
A22: 14 | B22: 1 of 1 | C22: Procter & Gamble Employer Spotlight: Graduate Careers & Recruitment | D22: Other / Employer-led event | E22: On Campus | F22: On Campus: Canary Wharf Level 50, SW54 Lecture Theatre | G22: 46309 | H22: =TEXT(G22,"ddd") -> Wed | I22: 0.54166667 | J22: 0.58333333 | K22: =ROUND((J22-I22)*24,2) -> 1 | L22: Join representatives from Procter & Gamble (P&G) to gain insight into careers, graduate recruitment and leadership development at one of the world's leading consumer goods companies. The session will provide an overview of opportunities available now | N22: 1-100 | O22: UCL Careers (uclcareers.targetconnect.net), captured 13-Oct-2026
A23: 15 | B23: 1 of 1 | C23: Shape Your International Future: HKU Business School Masters Info Session | D23: Other / Employer-led event | E23: On Campus | F23: On Campus: IOE - 20 Bedford Way C3.11 | G23: 46309 | H23: =TEXT(G23,"ddd") -> Wed | I23: 0.55208333 | J23: 0.61458333 | K23: =ROUND((J23-I23)*24,2) -> 1.5 | L23: Thinking about postgraduate study outside the UK and how to stand out in today's competitive job market? | N23: 1-100 | O23: UCL Careers (uclcareers.targetconnect.net), captured 13-Oct-2026
A24: 16 | B24: 1 of 1 | C24: Expedia Group Internship Insight Day (Office Visit) | D24: Other / Employer-led event | E24: Off Campus | F24: Off Campus | G24: 46309 | H24: =TEXT(G24,"ddd") -> Wed | I24: 0.57291667 | J24: 0.66666667 | K24: =ROUND((J24-I24)*24,2) -> 2.25 | L24: Are you graduating in 2028 and curious about what an internship at Expedia Group could look like? Join the Expedia Group for an exciting and immersive afternoon designed to set you up for success and help you prepare for your internship application. | N24: 1-100 | O24: UCL Careers (uclcareers.targetconnect.net), captured 13-Oct-2026
A25: 17 | B25: 1 of 1 | C25: Being Self-Employed/Freelancing Your Way: Different Brains, Different Ways of Working | D25: Other / Employer-led event | E25: Virtual | F25: Virtual event / Online webinar | G25: 46309 | H25: =TEXT(G25,"ddd") -> Wed | I25: 0.58333333 | J25: 0.64583333 | K25: =ROUND((J25-I25)*24,2) -> 1.5 | L25: This interactive workshop explores how neurodivergent people can build freelance (self-employed) and independent careers around the ways they work best when working in the Creative and Cultural Industries. | N25: 1-100 | O25: UCL Careers (uclcareers.targetconnect.net), captured 13-Oct-2026
A26: 18 | B26: 1 of 1 | C26: WORKING IN A GLOBAL WORLD - 2: How to Better Navigate a Complex World | D26: Working in a Global World | E26: On Campus | F26: On Campus: UCL Careers - 4th Floor Seminar Room (413) | G26: 46309 | H26: =TEXT(G26,"ddd") -> Wed | I26: 0.60416667 | J26: 0.70833333 | K26: =ROUND((J26-I26)*24,2) -> 2.5 | L26: The second session in the Cross-Cultural Communication strand is a deeper dive into beliefs, values, identity, and how they intersect. You will walk out the door with more frameworks to start using in your own life. | N26: 1-100 | O26: UCL Careers (uclcareers.targetconnect.net), captured 13-Oct-2026
A27: 19 | B27: 1 of 1 | C27: Get Hired! - Online Tests and Video Interview Prep | D27: Get Hired! | E27: On Campus | F27: On Campus: Canary Wharf Level 49, 49.01 Teaching Room | G27: 46309 | H27: =TEXT(G27,"ddd") -> Wed | I27: 0.60416667 | J27: 0.66666667 | K27: =ROUND((J27-I27)*24,2) -> 1.5 | L27: Work on your elevator pitch and practice your networking skills to make a fantastic first impression with employers. | N27: 1-100 | O27: UCL Careers (uclcareers.targetconnect.net), captured 13-Oct-2026
... A34: 26 | B34: 1 of 1 | C34: Launch Your Career with AlphaSights Asia - On-the-Spot Interviews Available | D34: Other / Employer-led event | E34: On Campus | F34: On Campus: Canary Wharf Level 49, 49.02 Teaching Room | G34: 46310 | H34: =TEXT(G34,"ddd") -> Thu | I34: 0.76041667 | J34: 0.80208333 | K34: =ROUND((J34-I34)*24,2) -> 1 | L34: Join us for an exclusive employer presentation hosted by AlphaSights, a global information services company specialising in connecting clients with expert knowledge to support informed business decisions. | N34: 1-100 | O34: UCL Careers (uclcareers.targetconnect.net), captured 13-Oct-2026
A35: 27 | B35: 1 of 1 | C35: Career Essentials: Application Forms and Cover Letters | D35: Career Essentials | E35: Not stated | G35: 46311 | H35: =TEXT(G35,"ddd") -> Fri | I35: 0.54166667 | J35: 0.58333333 | K35: =ROUND((J35-I35)*24,2) -> 1 | L35: Discover how to showcase your motivation and competency-based skills in your cover letter and on application materials. | N35: 1-100 | O35: UCL Careers (uclcareers.targetconnect.net), captured 13-Oct-2026
A36: 28 | B36: 1 of 1 | C36: Employer-led Skills Programme: One to One CV & Application Checking with Amazon | D36: Employer-led Skills Programme | E36: On Campus | F36: On Campus: UCL Careers (2) | G36: 46311 | H36: =TEXT(G36,"ddd") -> Fri | I36: 0.58333333 | J36: 0.70138889 | K36: =ROUND((J36-I36)*24,2) -> 2.83 | L36: Want expert employer feedback on your CV or application before you submit it? Participate in a one-to-one CV & Application Checking with a graduate employer. | N36: 1-100 | O36: UCL Careers (uclcareers.targetconnect.net), captured 13-Oct-2026
A37: 29 | B37: 1 of 1 | C37: Museum Collections in Practice: Careers, Collaboration and Decision-Making | D37: Other / Employer-led event | E37: On Campus | F37: On Campus: IOE - 20 Bedford Way - Room 822 | G37: 46311 | H37: =TEXT(G37,"ddd") -> Fri | I37: 0.70833333 | J37: 0.79166667 | K37: =ROUND((J37-I37)*24,2) -> 2 | L37: In this interactive workshop with UCL alumna Sara Mittica, you'll gain an insight into the world of museum collections and explore some of the challenges involved in balancing access, preservation, risk, resources and public benefit. | N37: 1-100 | O37: UCL Careers (uclcareers.targetconnect.net), captured 13-Oct-2026
A38: 30 | B38: 1 of 1 | C38: BCG UK International: Meet Our Global Offices | London | D38: Other / Employer-led event | E38: Not stated | G38: 46311 | H38: =TEXT(G38,"ddd") -> Fri | I38: 0.77083333 | J38: 0.85416667 | K38: =ROUND((J38-I38)*24,2) -> 2 | L38: Interested in starting your BCG career abroad? Join us in London to meet consultants and recruiters from BCG offices across Europe, Southeast Asia and the Caspian Region, and explore where an international career with BCG could take you. | N38: 1-100 | O38: UCL Careers (uclcareers.targetconnect.net), captured 13-Oct-2026
A39: 31 | B39: 1 of 2 | C39: Hong Kong · Global Talent & Career Showcase @London | D39: Other / Employer-led event | E39: Off Campus | F39: Off Campus | G39: 46312 | H39: =TEXT(G39,"ddd") -> Sat | I39: 0.4375 | J39: 0.70833333 | K39: =ROUND((J39-I39)*24,2) -> 6.5 | L39: Your Future in Hong Kong Starts Here | N39: 1-100 | O39: UCL Careers (uclcareers.targetconnect.net), captured 13-Oct-2026
A40: 31 | B40: 2 of 2 | C40: Hong Kong · Global Talent & Career Showcase @London | D40: Other / Employer-led event | E40: Off Campus | F40: Off Campus | G40: 46313 | H40: =TEXT(G40,"ddd") -> Sun | I40: 0.4375 | J40: 0.66666667 | K40: =ROUND((J40-I40)*24,2) -> 5.5 | L40: Your Future in Hong Kong Starts Here | N40: 1-100 | O40: UCL Careers (uclcareers.targetconnect.net), captured 13-Oct-2026
A41: 32 | B41: 1 of 1 | C41: On Campus Employer Pop-Up with : Deloitte | D41: Employer Presentation / Pop-Up | E41: On Campus | F41: On Campus: Wilkins Main Quad | G41: 46314 | H41: =TEXT(G41,"ddd") -> Mon | I41: 0.4375 | J41: 0.66666667 | K41: =ROUND((J41-I41)*24,2) -> 5.5 | L41: Want to learn more about what Deloitte is all about? We're inviting you to our "Meet Your Future" activation this autumn, to discover if a career with us could be right for you. | N41: 1-100 | O41: UCL Careers (uclcareers.targetconnect.net), captured 13-Oct-2026
A42: 33 | B42: 1 of 1 | C42: Career Essentials Group Work: Cover Letter Session | D42: Career Essentials Group Work | E42: Virtual | F42: Virtual event / Online webinar | G42: 46314 | H42: =TEXT(G42,"ddd") -> Mon | I42: 0.54166667 | J42: 0.57638889 | K42: =ROUND((J42-I42)*24,2) -> 0.83 | L42: Small group work Career Essentials session focusing on learning the key concepts that make up a good cover letter, reviewing your own work and providing peer-to-peer feedback. | N42: 1-100 | O42: UCL Careers (uclcareers.targetconnect.net), captured 13-Oct-2026
A43: 34 | B43: 1 of 1 | C43: PhD in the Life & Health Sciences Overview | D43: Life & Health Sciences | E43: Not stated | G43: 46314 | H43: =TEXT(G43,"ddd") -> Mon | I43: 0.54166667 | J43: 0.58333333 | K43: =ROUND((J43-I43)*24,2) -> 1 | L43: This session will provide an overview of doctoral study in the UK and help you explore your options before making an informed decision. The session will finish with a dedicated Q&A. | N43: 1-100 | O43: UCL Careers (uclcareers.targetconnect.net), captured 13-Oct-2026
A44: 35 | B44: 1 of 1 | C44: On Campus Employer Presentation: OIST - Okinawa Institute of Science and Technology | D44: Employer Presentation / Pop-Up | E44: On Campus | F44: On Campus: UCL Careers - 4th Floor Seminar Room (413) | G44: 46314 | H44: =TEXT(G44,"ddd") -> Mon | I44: 0.72916667 | J44: 0.79166667 | K44: =ROUND((J44-I44)*24,2) -> 1.5 | L44: Join us for an information session to learn about our fully funded research opportunities at Okinawa Institute of Science and Technology (OIST). | N44: 1-100 | O44: UCL Careers (uclcareers.targetconnect.net), captured 13-Oct-2026
A45: 36 | B45: 1 of 1 | C45: Career Lab - Using LinkedIn for a Purpose | D45: Career Lab | E45: On Campus | F45: On Campus: Canary Wharf Level 49, 49.02E Seminar Room | G45: 46315 | H45: =TEXT(G45,"ddd") -> Tue | I45: 0.39583333 | J45: 0.47916667 | K45: =ROUND((J45-I45)*24,2) -> 2 | L45: Learn how to to use LinkedIn to achieve a specific purpose through analysing scenarios and reflecting on success stories. | N45: 1-100 | O45: UCL Careers (uclcareers.targetconnect.net), captured 13-Oct-2026
A46: 37 | B46: 1 of 6 | C46: eCareersGrad MasterClass: Interview Success: Watch. Learn. Perform. | D46: eCareersGrad MasterClass | E46: Virtual | F46: Virtual event / Online webinar | G46: 46315 | H46: =TEXT(G46,"ddd") -> Tue | I46: 0.50694444 | J46: 0.54166667 | K46: =ROUND((J46-I46)*24,2) -> 0.83 | L46: An information session delivered by eCareersGrad with time for questions and answers. | N46: 1-100 | O46: UCL Careers (uclcareers.targetconnect.net), captured 13-Oct-2026
A47: 37 | B47: 2 of 6 | C47: eCareersGrad MasterClass: Interview Success: Watch. Learn. Perform. | D47: eCareersGrad MasterClass | E47: Virtual | F47: Virtual event / Online webinar | G47: 46329 | H47: =TEXT(G47,"ddd") -> Tue | I47: 0.50694444 | J47: 0.54166667 | K47: =ROUND((J47-I47)*24,2) -> 0.83 | L47: An information session delivered by eCareersGrad with time for questions and answers. | N47: 1-100 | O47: UCL Careers (uclcareers.targetconnect.net), captured 13-Oct-2026
A48: 37 | B48: 3 of 6 | C48: eCareersGrad MasterClass: Interview Success: Watch. Learn. Perform. | D48: eCareersGrad MasterClass | E48: Virtual | F48: Virtual event / Online webinar | G48: 46335 | H48: =TEXT(G48,"ddd") -> Mon | I48: 0.50694444 | J48: 0.54166667 | K48: =ROUND((J48-I48)*24,2) -> 0.83 | L48: An information session delivered by eCareersGrad with time for questions and answers. | N48: 1-100 | O48: UCL Careers (uclcareers.targetconnect.net), captured 13-Oct-2026
A49: 37 | B49: 4 of 6 | C49: eCareersGrad MasterClass: Interview Success: Watch. Learn. Perform. | D49: eCareersGrad MasterClass | E49: Virtual | F49: Virtual event / Online webinar | G49: 46344 | H49: =TEXT(G49,"ddd") -> Wed | I49: 0.50694444 | J49: 0.54166667 | K49: =ROUND((J49-I49)*24,2) -> 0.83 | L49: An information session delivered by eCareersGrad with time for questions and answers. | N49: 1-100 | O49: UCL Careers (uclcareers.targetconnect.net), captured 13-Oct-2026
A50: 37 | B50: 5 of 6 | C50: eCareersGrad MasterClass: Interview Success: Watch. Learn. Perform. | D50: eCareersGrad MasterClass | E50: Virtual | F50: Virtual event / Online webinar | G50: 46352 | H50: =TEXT(G50,"ddd") -> Thu | I50: 0.50694444 | J50: 0.54166667 | K50: =ROUND((J50-I50)*24,2) -> 0.83 | L50: An information session delivered by eCareersGrad with time for questions and answers. | N50: 1-100 | O50: UCL Careers (uclcareers.targetconnect.net), captured 13-Oct-2026
A51: 37 | B51: 6 of 6 | C51: eCareersGrad MasterClass: Interview Success: Watch. Learn. Perform. | D51: eCareersGrad MasterClass | E51: Virtual | F51: Virtual event / Online webinar | G51: 46358 | H51: =TEXT(G51,"ddd") -> Wed | I51: 0.50694444 | J51: 0.54166667 | K51: =ROUND((J51-I51)*24,2) -> 0.83 | L51: An information session delivered by eCareersGrad with time for questions and answers. | N51: 1-100 | O51: UCL Careers (uclcareers.targetconnect.net), captured 13-Oct-2026
A52: 38 | B52: 1 of 1 | C52: Career Essentials: LinkedIn - Sourcing Opportunities and Raising Your Profile | D52: Career Essentials | E52: Not stated | G52: 46315 | H52: =TEXT(G52,"ddd") -> Tue | I52: 0.54166667 | J52: 0.58333333 | K52: =ROUND((J52-I52)*24,2) -> 1 | L52: LinkedIn is an excellent source of networking and opportunities - learn how to update your profile and use the platform to its full capacity in this session. | N52: 1-100 | O52: UCL Careers (uclcareers.targetconnect.net), captured 13-Oct-2026
A53: 39 | B53: 1 of 1 | C53: Nomura Banking Trek: Office Visit and Insight Day - London HQ | D53: Other / Employer-led event | E53: Off Campus | F53: Off Campus | G53: 46315 | H53: =TEXT(G53,"ddd") -> Tue | I53: 0.58333333 | J53: 0.70833333 | K53: =ROUND((J53-I53)*24,2) -> 3 | L53: PLEASE NOTE: This is an insight day limited to selected people who fulfil the requirements for Nomura's graduate and internship roles. You will have to fill out a MS form and we will contact you prior the visit of the outcome. | N53: 1-100 | O53: UCL Careers (uclcareers.targetconnect.net), captured 13-Oct-2026
A54: 40 | B54: 1 of 1 | C54: BossUp: Understanding AI Readiness Webinar | D54: Other / Employer-led event | E54: Virtual | F54: Virtual event / Online webinar | G54: 46315 | H54: =TEXT(G54,"ddd") -> Tue | I54: 0.70833333 | J54: 0.79166667 | K54: =ROUND((J54-I54)*24,2) -> 2 | L54: UCL Careers, in partnership with BossUp, are looking at what AI readiness really means beyond simply using tools such as ChatGPT and how you can start developing now to improve your future employability. | N54: 1-100 | O54: UCL Careers (uclcareers.targetconnect.net), captured 13-Oct-2026
A55: 41 | B55: 1 of 1 | C55: Employer-Led Skills Panel : Commercial Awareness (what it is, why you need it and how to show it) with graduate recruiters | D55: Employer-led Skills Programme | E55: Virtual | F55: Virtual event / Online webinar | G55: 46315 | H55: =TEXT(G55,"ddd") -> Tue | I55: 0.70833333 | J55: 0.77083333 | K55: =ROUND((J55-I55)*24,2) -> 1.5 | L55: Employer-led panel discussion on developing commercial awareness skills, learn the importance of it, the need for it and how to show it. | M55: OC&C Strategy Consultants | N55: 1-100 | O55: UCL Careers (uclcareers.targetconnect.net), captured 13-Oct-2026
A56: 42 | B56: 1 of 1 | C56: Cathay Early Careers Engagement Session: Career Sharing, Insider Tips and Networking | D56: Other / Employer-led event | E56: On Campus | F56: On Campus: 1-19 Torrington Place: Room G12 | G56: 46315 | H56: =TEXT(G56,"ddd") -> Tue | I56: 0.77083333 | J56: 0.83333333 | K56: =ROUND((J56-I56)*24,2) -> 1.5 | L56: Join Cathay at UCL to explore graduate, internship and cadet pilot opportunities in Hong Kong. Learn about its business and culture, gain practical CV and interview tips, and connect with the Talent Acquisition Team. | N56: 1-100 | O56: UCL Careers (uclcareers.targetconnect.net), captured 13-Oct-2026
A57: 43 | B57: 1 of 1 | C57: The 2-Hour Grad Scheme: Black History Month Edition | D57: Other / Employer-led event | E57: On Campus | F57: On Campus: Winter Garden (30 Guilford Street) in UCL GOSICH - Philip Ullman Wing | G57: 46315 | H57: =TEXT(G57,"ddd") -> Tue | I57: 0.77083333 | J57: 0.85416667 | K57: =ROUND((J57-I57)*24,2) -> 2 | L57: This unique event is designed to give students and graduates the opportunity to hear directly from professionals who have successfully navigated their careers, overcome challenges and made a meaningful impact in their fields. | N57: 1-100 | O57: UCL Careers (uclcareers.targetconnect.net), captured 13-Oct-2026
A58: 44 | B58: 1 of 1 | C58: Swire Management Programme 2027: Shaping Future Business Leaders | D58: Other / Employer-led event | E58: Off Campus | F58: Off Campus | G58: 46315 | H58: =TEXT(G58,"ddd") -> Tue | I58: 0.80208333 | J58: 0.85416667 | K58: =ROUND((J58-I58)*24,2) -> 1.25 | L58: Join us for an exciting career presentation in London. Discover how our programme can propel you towards a global leadership journey! | N58: 1-100 | O58: UCL Careers (uclcareers.targetconnect.net), captured 13-Oct-2026
A59: 45 | B59: 1 of 1 | C59: Discover JPMorganChase 2027 Asia Analyst Development Program | D59: Other / Employer-led event | E59: Virtual | F59: Virtual event / Online webinar | G59: 46316 | H59: =TEXT(G59,"ddd") -> Wed | I59: 0.375 | J59: 0.4375 | K59: =ROUND((J59-I59)*24,2) -> 1.5 | L59: Interested in financial services in Southeast Asia? Join JPMorganChase to learn about the Asia Analyst Development Program (AADP) | N59: 1-100 | O59: UCL Careers (uclcareers.targetconnect.net), captured 13-Oct-2026
A60: 46 | B60: 1 of 1 | C60: How to prepare for psychometric tests with CIMA | D60: Other / Employer-led event | E60: Virtual | F60: Virtual event / Online webinar | G60: 46316 | H60: =TEXT(G60,"ddd") -> Wed | I60: 0.5 | J60: 0.54166667 | K60: =ROUND((J60-I60)*24,2) -> 1 | L60: Psychometric testing has become increasingly popular with employers in the recruitment of their apprenticeships, internships, placements, graduate roles and jobs at all levels. Join a Student Recruitment specialist at CIMA to find out more. | M60: CIMA | N60: 1-100 | O60: UCL Careers (uclcareers.targetconnect.net), captured 13-Oct-2026
A61: 47 | B61: 1 of 1 | C61: Keeta Campus Recruitment 2027 Online Info Session 美团国际化业务 Keeta · 2027届校园线上宣讲会 | D61: Other / Employer-led event | E61: Not stated | G61: 46316 | H61: =TEXT(G61,"ddd") -> Wed | I61: 0.5 | J61: 0.54166667 | K61: =ROUND((J61-I61)*24,2) -> 1 | L61: Keeta 是全球领先外卖平台美团旗下的独立品牌。我们肩负着"帮大家吃得更好，生活更好"的使命，依托美团深耕中国市场16年的技术与运营积淀，我们正引领全球餐饮与商品即时配送服务的创新与发展。来 Keeta，机会无界，成长无限！ | N61: 1-100 | O61: UCL Careers (uclcareers.targetconnect.net), captured 13-Oct-2026
A62: 48 | B62: 1 of 1 | C62: Exploring Career Opportunities with HSBC China (Mandarin Session 普通话) | D62: Other / Employer-led event | E62: Virtual | F62: Virtual event / Online webinar | G62: 46316 | H62: =TEXT(G62,"ddd") -> Wed | I62: 0.53125 | J62: 0.58333333 | K62: =ROUND((J62-I62)*24,2) -> 1.25 | L62: Join representatives from HSBC China for a webinar exploring the bank's business in Chinese mainland, career pathways, and 2027 graduate and internship opportunities | N62: 1-100 | O62: UCL Careers (uclcareers.targetconnect.net), captured 13-Oct-2026
A63: 49 | B63: 1 of 1 | C63: Masterclass in consulting: Case study interviews | D63: Other / Employer-led event | E63: On Campus | F63: On Campus: Canary Wharf Level 49, 49.01 Teaching Room | G63: 46316 | H63: =TEXT(G63,"ddd") -> Wed | I63: 0.53125 | J63: 0.59375 | K63: =ROUND((J63-I63)*24,2) -> 1.5 | L63: Prepare for the graduate recruitment cycle in this interactive/panel/informational session. Include the pathway interest if relevant, and any key words in this description. | N63: 1-100 | O63: UCL Careers (uclcareers.targetconnect.net), captured 13-Oct-2026
A64: 50 | B64: 1 of 1 | C64: Skills East: Crafting A Standout CV & Cover Letter | D64: Skills East | E64: On Campus | F64: UCL East Campus: Marshgate Building: Room 612 | G64: 46316 | H64: =TEXT(G64,"ddd") -> Wed | I64: 0.54166667 | J64: 0.58333333 | K64: =ROUND((J64-I64)*24,2) -> 1 | L64: In Person small group work Career Essentials session focusing on developing and writing an effective CV and cover letter from UCL Careers staff and peers. | N64: 1-100 | O64: UCL Careers (uclcareers.targetconnect.net), captured 13-Oct-2026
A65: 51 | B65: 1 of 1 | C65: Career Essentials Group Work: Personal Statements for Postgraduate Degrees | D65: Career Essentials Group Work | E65: On Campus | F65: On Campus: UCL Careers - 4th Floor Seminar Room (413) | G65: 46316 | H65: =TEXT(G65,"ddd") -> Wed | I65: 0.54166667 | J65: 0.57638889 | K65: =ROUND((J65-I65)*24,2) -> 0.83 | L65: Small group work session focusing on the importance of tailoring applications, reviewing an example personal statement in a small group setting and how to apply this to individual personal statements. | N65: 1-100 | O65: UCL Careers (uclcareers.targetconnect.net), captured 13-Oct-2026
A66: 52 | B66: 1 of 1 | C66: Digital Advertising in 2026: Channels, Data, AI and Global Growth | D66: Other / Employer-led event | E66: On Campus | F66: On Campus: IOE - 20 Bedford Way - Room 828 | G66: 46316 | H66: =TEXT(G66,"ddd") -> Wed | I66: 0.54166667 | J66: 0.625 | K66: =ROUND((J66-I66)*24,2) -> 2 | L66: In this practical workshop, The Digital Lighthouse team will explore with students: How global brands choose channels, structure campaigns and measure performance and how AI is changing both the work and the skills employers value. | N66: 1-100 | O66: UCL Careers (uclcareers.targetconnect.net), captured 13-Oct-2026
A67: 53 | B67: 1 of 1 | C67: Real Estate Private Equity and the Investment Committee | D67: Other / Employer-led event | E67: On Campus | F67: UCL East Campus: One Pool Street Building: Room 105 (Cinema) | G67: 46316 | H67: =TEXT(G67,"ddd") -> Wed | I67: 0.58333333 | J67: 0.66666667 | K67: =ROUND((J67-I67)*24,2) -> 2 | L67: Develop key skills relevant to a career in finance and investments | N67: 1-100 | O67: UCL Careers (uclcareers.targetconnect.net), captured 13-Oct-2026
A68: 54 | B68: 1 of 1 | C68: Navigating your Visa Options with Paragon Law | D68: Other / Employer-led event | E68: Virtual | F68: Virtual event / Online webinar | G68: 46316 | H68: =TEXT(G68,"ddd") -> Wed | I68: 0.60416667 | J68: 0.66666667 | K68: =ROUND((J68-I68)*24,2) -> 1.5 | L68: Understand your Visa options and timeline for now and after your studies | N68: 1-100 | O68: UCL Careers (uclcareers.targetconnect.net), captured 13-Oct-2026
A69: 55 | B69: 1 of 1 | C69: WORKING IN A GLOBAL WORLD SERIES - 3: What Have Emotions Got to Do with It? | D69: Working in a Global World | E69: On Campus | F69: On Campus: 40 Bernard Street: Room 412 | G69: 46316 | H69: =TEXT(G69,"ddd") -> Wed | I69: 0.60416667 | J69: 0.70833333 | K69: =ROUND((J69-I69)*24,2) -> 2.5 | L69: In WGW 3, we will continue exploring beliefs, values, and identity, but from a new angle: emotions. The Awareness and Knowledge gain will help you manage, and even accelerate, the often uncomfortable process of engaging with another culture. | N69: 1-100 | O69: UCL Careers (uclcareers.targetconnect.net), captured 13-Oct-2026
A70: 56 | B70: 1 of 1 | C70: Risk, compliance & governance fundamentals: Managing risk, internal controls & regulatory expectations with Fide Consulting | D70: Other / Employer-led event | E70: On Campus | F70: On Campus: Canary Wharf Level 49, 49.02 Teaching Room | G70: 46316 | H70: =TEXT(G70,"ddd") -> Wed | I70: 0.60416667 | J70: 0.65625 | K70: =ROUND((J70-I70)*24,2) -> 1.25 | L70: Get practical insights into how organisations manage risk, implement internal controls, and respond to evolving regulatory expectations. Delivered with industry expertise from Fide Consulting. | N70: 1-100 | O70: UCL Careers (uclcareers.targetconnect.net), captured 13-Oct-2026
A71: 57 | B71: 1 of 1 | C71: Tech, Data & AI Fair | D71: Careers Fair | E71: On Campus | F71: On Campus: IOE - 20 Bedford Way - Jeffery Hall LT (Rm 103) | G71: 46316 | H71: =TEXT(G71,"ddd") -> Wed | I71: 0.66666667 | J71: 0.79166667 | K71: =ROUND((J71-I71)*24,2) -> 3 | L71: The Tech, Data & AI Careers Fair is your opportunity to meet with a wide range of organisations working in this popular sector. | N71: 1-100 | O71: UCL Careers (uclcareers.targetconnect.net), captured 13-Oct-2026
A72: 58 | B72: 1 of 1 | C72: On Campus Employer Pop-Up with : Macquarie campus activation | D72: Employer Presentation / Pop-Up | E72: On Campus | F72: On Campus: Wilkins Main Quad | G72: 46317 | H72: =TEXT(G72,"ddd") -> Thu | I72: 0.45833333 | J72: 0.58333333 | K72: =ROUND((J72-I72)*24,2) -> 3 | L72: Join Macquarie on campus at UCL to learn more about our 2027 Spring Insight Week, Summer Internship and Graduate opportunities. | N72: 1-100 | O72: UCL Careers (uclcareers.targetconnect.net), captured 13-Oct-2026
A73: 59 | B73: 1 of 1 | C73: On Campus Employer Presentation: Discover PwC: your future in a changing world | D73: Employer Presentation / Pop-Up | E73: On Campus | F73: On Campus: UCL Careers - 4th Floor Seminar Room (413) | G73: 46317 | H73: =TEXT(G73,"ddd") -> Thu | I73: 0.52083333 | J73: 0.58333333 | K73: =ROUND((J73-I73)*24,2) -> 1.5 | L73: You may have heard of the PwC name, but how much do you know about the work we do and the opportunities available? This guest lecture will introduce you to PwC, a professional services firm that brings together people, expertise and technology. | N73: 1-100 | O73: UCL Careers (uclcareers.targetconnect.net), captured 13-Oct-2026
A74: 60 | B74: 1 of 1 | C74: PhD in Life & Health Sciences — The Francis Crick Institute programme | D74: Life & Health Sciences | E74: Not stated | G74: 46317 | H74: =TEXT(G74,"ddd") -> Thu | I74: 0.54166667 | J74: 0.58333333 | K74: =ROUND((J74-I74)*24,2) -> 1 | L74: The Francis Crick Institute PhD Programme offers four years of interdisciplinary biomedical research and training. Hear from the programme team about the PhD Programme and the application process. | N74: 1-100 | O74: UCL Careers (uclcareers.targetconnect.net), captured 13-Oct-2026
A75: 61 | B75: 1 of 1 | C75: Careers Essentials: Interview Success | D75: Career Essentials | E75: Not stated | G75: 46317 | H75: =TEXT(G75,"ddd") -> Thu | I75: 0.54166667 | J75: 0.58333333 | K75: =ROUND((J75-I75)*24,2) -> 1 | L75: Prepare for your future interviews in this session where we discuss making first impressions, typical interview questions and ways to stand out. | N75: 1-100 | O75: UCL Careers (uclcareers.targetconnect.net), captured 13-Oct-2026
A76: 62 | B76: 1 of 1 | C76: Sector Insights: Navigating the Civil Service Fast Stream | D76: Sector Insights | E76: Virtual | F76: Virtual event / Online webinar | G76: 46317 | H76: =TEXT(G76,"ddd") -> Thu | I76: 0.54166667 | J76: 0.60416667 | K76: =ROUND((J76-I76)*24,2) -> 1.5 | L76: Looking for more information about the government's flagship graduate programme: The Civil Service Fast Stream? Join us for an online panel and Q&A event to hear Panellists share their reflections on the Civil Service Fast Stream. | N76: 1-100 | O76: UCL Careers (uclcareers.targetconnect.net), captured 13-Oct-2026
A77: 63 | B77: 1 of 1 | C77: (International Students) Networking Skills | D77: International Students | E77: On Campus | F77: On Campus: IOE - 20 Bedford Way - 728 | G77: 46317 | H77: =TEXT(G77,"ddd") -> Thu | I77: 0.66666667 | J77: 0.75 | K77: =ROUND((J77-I77)*24,2) -> 2 | L77: Networking Skills | N77: 1-100 | O77: UCL Careers (uclcareers.targetconnect.net), captured 13-Oct-2026
A78: 64 | B78: 1 of 1 | C78: Life & Health Sciences Careers Talk: Researching Career Options | D78: Life & Health Sciences | E78: Virtual | F78: Virtual event / Online webinar | G78: 46317 | H78: =TEXT(G78,"ddd") -> Thu | I78: 0.70833333 | J78: 0.75 | K78: =ROUND((J78-I78)*24,2) -> 1 | L78: Not sure what to do after your degree? Explore career options linked to your subject, discover ways to generate career ideas, learn how to research roles and sectors, and identify practical next steps to help shape your future career plans. | N78: 1-100 | O78: UCL Careers (uclcareers.targetconnect.net), captured 13-Oct-2026
A79: 65 | B79: 1 of 1 | C79: Creating Games That Teach: Designing a "2mins" Educational and Financial App | D79: Other / Employer-led event | E79: On Campus | F79: On Campus: IOE - 20 Bedford Way - Room 739 | G79: 46318 | H79: =TEXT(G79,"ddd") -> Fri | I79: 0.54166667 | J79: 0.625 | K79: =ROUND((J79-I79)*24,2) -> 2 | L79: In this interactive workshop, you'll get a behind-the-scenes look at how 2mins was developed before putting your own ideas to the test. | N79: 1-100 | O79: UCL Careers (uclcareers.targetconnect.net), captured 13-Oct-2026
A80: 66 | B80: 1 of 1 | C80: 2-Hour Science Graduate Scheme: Future Leaders Networking Forum | D80: Other / Employer-led event | E80: On Campus | F80: On Campus: Wilkins Building - Yellow Room (G17) | G80: 46318 | H80: =TEXT(G80,"ddd") -> Fri | I80: 0.70833333 | J80: 0.80555556 | K80: =ROUND((J80-I80)*24,2) -> 2.33 | L80: Explore your options. Meet current trainees. Discover where a graduate scheme could take you. | N80: 1-100 | O80: UCL Careers (uclcareers.targetconnect.net), captured 13-Oct-2026
A81: 67 | B81: 1 of 1 | C81: Employer - Led Skills Panel : Preparing for Assessment Centre graduate recruiters | D81: Employer-led Skills Panel | E81: On Campus | F81: On Campus: UCL Careers - 4th Floor Seminar Room (413) | G81: 46321 | H81: =TEXT(G81,"ddd") -> Mon | I81: 0.54166667 | J81: 0.60416667 | K81: =ROUND((J81-I81)*24,2) -> 1.5 | L81: A panel session featuring graduate employers offering guidance on how to prepare for assessment centre activities. | N81: 1-100 | O81: UCL Careers (uclcareers.targetconnect.net), captured 13-Oct-2026
A82: 68 | B82: 1 of 1 | C82: Career Essentials: Find and Fund a PhD | D82: Career Essentials | E82: Not stated | G82: 46321 | H82: =TEXT(G82,"ddd") -> Mon | I82: 0.54166667 | J82: 0.58333333 | K82: =ROUND((J82-I82)*24,2) -> 1 | L82: This session gives an overview into PhD application materials such as constructing a personal statement, academic CV and a research proposal. | N82: 1-100 | O82: UCL Careers (uclcareers.targetconnect.net), captured 13-Oct-2026
A83: 69 | B83: 1 of 1 | C83: Applying for a PhD in Life & Health Science | D83: Life & Health Sciences | E83: Not stated | G83: 46321 | H83: =TEXT(G83,"ddd") -> Mon | I83: 0.54166667 | J83: 0.58333333 | K83: =ROUND((J83-I83)*24,2) -> 1 | L83: This seminar will provide practical guidance on finding suitable PhD opportunities in the UK and navigating the application process. | N83: 1-100 | O83: UCL Careers (uclcareers.targetconnect.net), captured 13-Oct-2026
A84: 70 | B84: 1 of 1 | C84: Life & Health Science Fair | D84: Careers Fair | E84: Off Campus | F84: Off Campus | G84: 46321 | H84: =TEXT(G84,"ddd") -> Mon | I84: 0.70833333 | J84: 0.83333333 | K84: =ROUND((J84-I84)*24,2) -> 3 | L84: UCL, Imperial College London and King's College London invite you to this event. The Life and Health Science Careers Event is your opportunity to meet with a wide range of organisations working in this popular sector. | N84: 1-100 | O84: UCL Careers (uclcareers.targetconnect.net), captured 13-Oct-2026
A85: 71 | B85: 1 of 1 | C85: Career Lab - Consulting Case Skills Practice Session | D85: Career Lab | E85: On Campus | F85: On Campus: Canary Wharf Level 49, 49.02E Seminar Room | G85: 46322 | H85: =TEXT(G85,"ddd") -> Tue | I85: 0.39583333 | J85: 0.47916667 | K85: =ROUND((J85-I85)*24,2) -> 2 | L85: practice market sizing, interpreting case exhibits and your casing communication skills in small groups | N85: 1-100 | O85: UCL Careers (uclcareers.targetconnect.net), captured 13-Oct-2026
A86: 72 | B86: 1 of 1 | C86: Skills East: Job Interview Technique | D86: Skills East | E86: Virtual | F86: Virtual event / Online webinar | G86: 46322 | H86: =TEXT(G86,"ddd") -> Tue | I86: 0.5 | J86: 0.54166667 | K86: =ROUND((J86-I86)*24,2) -> 1 | L86: Online skills session focusing on learning the key techniques to prepare for an answer job interview questions from UCL Careers staff and peers. | N86: 1-100 | O86: UCL Careers (uclcareers.targetconnect.net), captured 13-Oct-2026
A87: 73 | B87: 1 of 1 | C87: Here East Part-Time Jobs Fair October 2026 | D87: Careers Fair | E87: In person (venue listed) | F87: Plexal, Ground Floor, Here East | G87: 46322 | H87: =TEXT(G87,"ddd") -> Tue | I87: 0.5 | J87: 0.625 | K87: =ROUND((J87-I87)*24,2) -> 3 | L87: Working alongside your studies is a brilliant way to increase your employability and network. On 27th October, we will host a jobs fair at Here East on the Queen Elizabeth Olympic Park. | N87: 1-100 | O87: UCL Careers (uclcareers.targetconnect.net), captured 13-Oct-2026
A88: 74 | B88: 1 of 1 | C88: Career Essentials: Your Future and How to Work Towards It | D88: Career Essentials | E88: Not stated | G88: 46322 | H88: =TEXT(G88,"ddd") -> Tue | I88: 0.54166667 | J88: 0.58333333 | K88: =ROUND((J88-I88)*24,2) -> 1 | L88: Thinking about what your life and career will look like post graduation from UCL? In this session our team discusses potential options and ways to help you get to your next steps. | N88: 1-100 | O88: UCL Careers (uclcareers.targetconnect.net), captured 13-Oct-2026
A89: 75 | B89: 1 of 1 | C89: Career Essentials Group Work: Using STAR to Showcase Skills | D89: Career Essentials Group Work | E89: Virtual | F89: Virtual event / Online webinar | G89: 46322 | H89: =TEXT(G89,"ddd") -> Tue | I89: 0.54166667 | J89: 0.57638889 | K89: =ROUND((J89-I89)*24,2) -> 0.83 | L89: Small group work Career Essentials session focusing on learning the STAR technique, which can be used as a tool during interviews to help answer questions and showcase your skills. | N89: 1-100 | O89: UCL Careers (uclcareers.targetconnect.net), captured 13-Oct-2026
A90: 76 | B90: 1 of 1 | C90: Powered by AI: An Evening with Amazon Web Services (AWS) | D90: Other / Employer-led event | E90: On Campus | F90: On Campus: IOE - 20 Bedford Way - Room W3.01 | G90: 46322 | H90: =TEXT(G90,"ddd") -> Tue | I90: 0.76041667 | J90: 0.85416667 | K90: =ROUND((J90-I90)*24,2) -> 2.25 | L90: Curious how AI is changing the way we learn, work and build careers? Join AWS experts and UCL alumni for insights into AI, real career journeys and practical advice, with opportunities to ask questions, take part in small-group mentoring and network. | N90: 1-100 | O90: UCL Careers (uclcareers.targetconnect.net), captured 13-Oct-2026
A91: 77 | B91: 1 of 1 | C91: Careers in China: Discover Your Strengths and Plan Your Next Steps 职通中国：看看你在求职这个丛林里，你是谁？ (Mandarin Session 普通话) | D91: Other / Employer-led event | E91: On Campus | F91: On Campus: Canary Wharf Level 49, 49.01 Teaching Room | G91: 46323 | H91: =TEXT(G91,"ddd") -> Wed | I91: 0.53125 | J91: 0.65625 | K91: =ROUND((J91-I91)*24,2) -> 3 | L91: 看看你在求职这个丛林里，你是谁？ 解锁你的竞争力专属标签 同步开启优质雇主秋招专属投递机会 | N91: 1-100 | O91: UCL Careers (uclcareers.targetconnect.net), captured 13-Oct-2026
A92: 78 | B92: 1 of 1 | C92: Explore Careers with Bloomberg | D92: Other / Employer-led event | E92: On Campus | F92: On Campus: Canary Wharf Level 50, NW54 Lecture Theatre | G92: 46323 | H92: =TEXT(G92,"ddd") -> Wed | I92: 0.53125 | J92: 0.60416667 | K92: =ROUND((J92-I92)*24,2) -> 1.75 | L92: This session will provide an introduction to Bloomberg, explore career opportunities across the business, and offer insights into how Bloomberg's data, technology, and news services support global financial markets. | N92: 1-100 | O92: UCL Careers (uclcareers.targetconnect.net), captured 13-Oct-2026
A93: 79 | B93: 1 of 1 | C93: Roundtable Chats with Industry Professionals | D93: Other / Employer-led event | E93: On Campus | F93: On Campus: Canary Wharf Level 49, 49.02 Teaching Room | G93: 46323 | H93: =TEXT(G93,"ddd") -> Wed | I93: 0.53125 | J93: 0.59375 | K93: =ROUND((J93-I93)*24,2) -> 1.5 | L93: Join for an interactive networking session where professionals from leading companies will host small-group discussions with students. Each professional will answer questions related to their career path/ industry, and then invite student questions. | N93: 1-100 | O93: UCL Careers (uclcareers.targetconnect.net), captured 13-Oct-2026
A94: 80 | B94: 1 of 1 | C94: PhD in Life & Health Sciences — HealthBRIDGE MRC Doctoral Landscape Award Programme | D94: Life & Health Sciences | E94: Not stated | G94: 46323 | H94: =TEXT(G94,"ddd") -> Wed | I94: 0.54166667 | J94: 0.58333333 | K94: =ROUND((J94-I94)*24,2) -> 1 | L94: The session will provide an overview of the HealthBRIDGE programme, including what makes a strong candidate and how to apply, followed by a live Q&A with the programme representative. The main session will be recorded | N94: 1-100 | O94: UCL Careers (uclcareers.targetconnect.net), captured 13-Oct-2026
A95: 81 | B95: 1 of 1 | C95: Life & Health Sciences Careers Talk: CVs, Cover Letters & Application Forms | D95: Life & Health Sciences | E95: Virtual | F95: Virtual event / Online webinar | G95: 46323 | H95: =TEXT(G95,"ddd") -> Wed | I95: 0.54166667 | J95: 0.58333333 | K95: =ROUND((J95-I95)*24,2) -> 1 | L95: Want to improve your CVs and applications? This session uses real Life & Health Sciences examples to show how to tailor your CV, write a compelling cover letter, tackle application form questions, and make the most of helpful resources. | N95: 1-100 | O95: UCL Careers (uclcareers.targetconnect.net), captured 13-Oct-2026
A96: 82 | B96: 1 of 1 | C96: (International Students) Part-time, Graduate, and Skilled Worker Job Hunting | D96: International Students | E96: On Campus | F96: On Campus: Bentham House, Denys Holland Lecture Theatre (Room SB31) | G96: 46323 | H96: =TEXT(G96,"ddd") -> Wed | I96: 0.5625 | J96: 0.625 | K96: =ROUND((J96-I96)*24,2) -> 1.5 | L96: Job Hunting UK | N96: 1-100 | O96: UCL Careers (uclcareers.targetconnect.net), captured 13-Oct-2026
A97: 83 | B97: 1 of 1 | C97: WORKING IN A GLOBAL WORLD SERIES - 4: Teamwork Across Cultures | D97: Working in a Global World | E97: On Campus | F97: On Campus: 40 Bernard Street: Room 412 | G97: 46323 | H97: =TEXT(G97,"ddd") -> Wed | I97: 0.60416667 | J97: 0.70833333 | K97: =ROUND((J97-I97)*24,2) -> 2.5 | L97: This experiential session will give you a chance to practice and consolidate the concepts and practical tips covered in the first three sessions. You will also practice some new tools for how to communicate despite differences. | N97: 1-100 | O97: UCL Careers (uclcareers.targetconnect.net), captured 13-Oct-2026
A98: 84 | B98: 1 of 1 | C98: Engineering & Built Environment Fair | D98: Careers Fair | E98: On Campus | F98: On Campus: IOE - 20 Bedford Way: Jeffery Hall LT (Rm 103) | G98: 46323 | H98: =TEXT(G98,"ddd") -> Wed | I98: 0.66666667 | J98: 0.79166667 | K98: =ROUND((J98-I98)*24,2) -> 3 | L98: The Engineering & Built Environment Careers Fair is your opportunity to meet with a wide range of organisations working in this popular sector. | N98: 1-100 | O98: UCL Careers (uclcareers.targetconnect.net), captured 13-Oct-2026
A99: 85 | B99: 1 of 1 | C99: Career Essentials: Better PhD applications | D99: Career Essentials | E99: Not stated | G99: 46324 | H99: =TEXT(G99,"ddd") -> Thu | I99: 0.54166667 | J99: 0.58333333 | K99: =ROUND((J99-I99)*24,2) -> 1 | L99: What to expect when applying to do a PhD and how to ensure your application is effective in getting you to interview | N99: 1-100 | O99: UCL Careers (uclcareers.targetconnect.net), captured 13-Oct-2026
A100: 86 | B100: 1 of 1 | C100: Careers in AI for Philosophers: Building the Rules for AI From First Principles | D100: Other / Employer-led event | E100: On Campus | F100: On Campus: 14 - 16 Taviton Street: Daryll Forde Seminar Room (230) | G100: 46324 | H100: =TEXT(G100,"ddd") -> Thu | I100: 0.72916667 | J100: 0.8125 | K100: =ROUND((J100-I100)*24,2) -> 2 | L100: Join us for this event looking at how your skills and knowledge as a philosopher can be applied within AI careers | N100: 1-100 | O100: UCL Careers (uclcareers.targetconnect.net), captured 13-Oct-2026
A101: 87 | B101: 1 of 1 | C101: Sector Insights: Building experience for a career in the non-profit sector | D101: Sector Insights | E101: Not stated | G101: 46324 | H101: =TEXT(G101,"ddd") -> Thu | I101: 0.72916667 | J101: 0.79166667 | K101: =ROUND((J101-I101)*24,2) -> 1.5 | L101: Join this event to hear from alumni and industry professionals about the skills and opportunities that helped them build a career in non-profit sector, and their advice on what you can be doing right now to stand out to recruiters. | N101: 1-100 | O101: UCL Careers (uclcareers.targetconnect.net), captured 13-Oct-2026
A102: 88 | B102: 1 of 1 | C102: Pitching Competition: The Big Idea Challenge - Headstart your career | D102: Other / Employer-led event | E102: On Campus | F102: On Campus: Roberts Building: G08 Sir David Davies LT | G102: 46324 | H102: =TEXT(G102,"ddd") -> Thu | I102: 0.75 | J102: 0.83333333 | K102: =ROUND((J102-I102)*24,2) -> 2 | L102: Explore how simple ideas can become real businesses. Add on CV, win prize and network with alumni | N102: 1-100 | O102: UCL Careers (uclcareers.targetconnect.net), captured 13-Oct-2026
A103: 89 | B103: 1 of 1 | C103: Data Science Meets Product Innovation: UCL × DataSpartan × GuruAI Challenge | D103: Other / Employer-led event | E103: On Campus | F103: On Campus: IOE - 20 Bedford Way - Room W3.01 | G103: 46324 | H103: =TEXT(G103,"ddd") -> Thu | I103: 0.76041667 | J103: 0.875 | K103: =ROUND((J103-I103)*24,2) -> 2.75 | L103: Join DataSpartan, GuruAI and the UCL Data Science Society for an interactive innovation competition exploring the future of AI-powered music education. Work in interdisciplinary teams to tackle a real industry challenge. | N103: 1-100 | O103: UCL Careers (uclcareers.targetconnect.net), captured 13-Oct-2026
A104: 90 | B104: 1 of 1 | C104: Employer-led Skills Programme: One to One Practice Interviews with F5 | D104: Employer-led Skills Programme | E104: Virtual | F104: Virtual event / Online webinar | G104: 46325 | H104: =TEXT(G104,"ddd") -> Fri | I104: 0.40625 | J104: 0.54166667 | K104: =ROUND((J104-I104)*24,2) -> 3.25 | L104: Want to practice your interview skills? Participate in this one-to-one practice interview session for the opportunity to practice and to receive expert feedback from a graduate recruiter. | M104: F5 | N104: 1-100 | O104: UCL Careers (uclcareers.targetconnect.net), captured 13-Oct-2026
A105: 91 | B105: 1 of 1 | C105: Career Essentials Group Work: CV Session | D105: Career Essentials Group Work | E105: On Campus | F105: On Campus: UCL Careers - 4th Floor Seminar Room (413) | G105: 46325 | H105: =TEXT(G105,"ddd") -> Fri | I105: 0.54166667 | J105: 0.57638889 | K105: =ROUND((J105-I105)*24,2) -> 0.83 | L105: Small group work Career Essentials session focusing on learning the key concepts that make up a good CV and getting feedback on your own CV from UCL Careers staff and peers. | N105: 1-100 | O105: UCL Careers (uclcareers.targetconnect.net), captured 13-Oct-2026
A106: 92 | B106: 1 of 1 | C106: Employer-led Skills workshop: Creativity for career impact with Aveea | D106: Employer-led Skills Programme | E106: On Campus | F106: On Campus: UCL Careers - 4th Floor Seminar Room (413) | G106: 46328 | H106: =TEXT(G106,"ddd") -> Mon | I106: 0.52083333 | J106: 0.58333333 | K106: =ROUND((J106-I106)*24,2) -> 1.5 | L106: This practice workshop led by a graduate employer, provides an opportunity to practice and better understand your creativity skills and how it can be beneficial during your career journey. | N106: 1-100 | O106: UCL Careers (uclcareers.targetconnect.net), captured 13-Oct-2026
...

Sheet Summary
A1: UCL Careers events listing - summary (all figures are formulas over the 'All Sessions' sheet)
A3: Distinct events listed | B3: =MAX('All Sessions'!A2:A169) -> 153
A4: Scheduled sessions (rows) | B4: =COUNTA('All Sessions'!C2:C169) -> 168
A5: Earliest session | B5: =MIN('All Sessions'!G2:G169) -> 46303
A6: Latest session | B6: =MAX('All Sessions'!G2:G169) -> 46444
A8: Sessions by delivery mode | B8: Sessions
A9: Virtual | B9: =COUNTIF('All Sessions'!$E$2:$E$169,A9) -> 53
A10: On Campus | B10: =COUNTIF('All Sessions'!$E$2:$E$169,A10) -> 72
A11: Off Campus | B11: =COUNTIF('All Sessions'!$E$2:$E$169,A11) -> 8
A12: In person (venue listed) | B12: =COUNTIF('All Sessions'!$E$2:$E$169,A12) -> 1
A13: Not stated | B13: =COUNTIF('All Sessions'!$E$2:$E$169,A13) -> 34
A14: Total | B14: =SUM(B9:B13) -> 168
A16: Sessions by month | B16: Sessions
A17: Oct 2026 | B17: =COUNTIFS('All Sessions'!$G$2:$G$169,">="&DATE(2026,10,1),'All Sessions'!$G$2:$G$169,"<"&DATE(2026,11,1)) -> 97
A18: Nov 2026 | B18: =COUNTIFS('All Sessions'!$G$2:$G$169,">="&DATE(2026,11,1),'All Sessions'!$G$2:$G$169,"<"&DATE(2026,12,1)) -> 50
A19: Dec 2026 | B19: =COUNTIFS('All Sessions'!$G$2:$G$169,">="&DATE(2026,12,1),'All Sessions'!$G$2:$G$169,"<"&DATE(2027,1,1)) -> 15
A20: Jan 2027 | B20: =COUNTIFS('All Sessions'!$G$2:$G$169,">="&DATE(2027,1,1),'All Sessions'!$G$2:$G$169,"<"&DATE(2027,2,1)) -> 2
A21: Feb 2027 | B21: =COUNTIFS('All Sessions'!$G$2:$G$169,">="&DATE(2027,2,1),'All Sessions'!$G$2:$G$169,"<"&DATE(2027,3,1)) -> 4
A22: Total | B22: =SUM(B17:B21) -> 168
A24: Sessions by series / programme | B24: Sessions
A25: Career Essentials | B25: =COUNTIF('All Sessions'!$D$2:$D$169,A25) -> 26
A26: Career Essentials Group Work | B26: =COUNTIF('All Sessions'!$D$2:$D$169,A26) -> 15
A27: Career Lab | B27: =COUNTIF('All Sessions'!$D$2:$D$169,A27) -> 4
A28: Careers Fair | B28: =COUNTIF('All Sessions'!$D$2:$D$169,A28) -> 6
A29: Employer Presentation / Pop-Up | B29: =COUNTIF('All Sessions'!$D$2:$D$169,A29) -> 5
A30: Employer-led Skills Panel | B30: =COUNTIF('All Sessions'!$D$2:$D$169,A30) -> 3
A31: Employer-led Skills Programme | B31: =COUNTIF('All Sessions'!$D$2:$D$169,A31) -> 14
A32: Get Hired! | B32: =COUNTIF('All Sessions'!$D$2:$D$169,A32) -> 2
A33: International Students | B33: =COUNTIF('All Sessions'!$D$2:$D$169,A33) -> 6
A34: Life & Health Sciences | B34: =COUNTIF('All Sessions'!$D$2:$D$169,A34) -> 12
A35: Other / Employer-led event | B35: =COUNTIF('All Sessions'!$D$2:$D$169,A35) -> 49
A36: Sector Insights | B36: =COUNTIF('All Sessions'!$D$2:$D$169,A36) -> 2
... A39: eCareersGrad MasterClass | B39: =COUNTIF('All Sessions'!$D$2:$D$169,A39) -> 18
A40: Total | B40: =SUM(B25:B39) -> 168
A42: Notes
A43: Source: UCL Careers 'Search events' listing (153 results), two PDF captures dated 13-Oct-2026 21:52/21:53.
A44: One row per scheduled date; events offered on several dates (e.g. eCareersGrad MasterClasses) repeat with 'Session x of y'.
A45: 'Event Series / Programme' and 'Delivery Mode' are derived from the title and venue line respectively; all other fields are transcribed as listed.
A46: 'Delivery Mode' = 'Not stated' where the listing shows no venue/format line; 'In person (venue listed)' where a venue is given without an On/Off Campus label.
A47: 'Featured Organisation' records the sponsor logo shown beneath the description, where one appeared.
A48: Day and Duration are formulas and recalculate if a date or time is edited.
